LinkedInWebScraper/__init__.py
LinkedInWebScraper/job_data_cleaner.py
LinkedInWebScraper/job_description_processor.py
LinkedInWebScraper/job_scraper.py
LinkedInWebScraper/job_scraper_advanced_config.py
LinkedInWebScraper/job_scraper_config.py
LinkedInWebScraper/job_scraper_config_factory.py
LinkedInWebScraper/job_title_classifier.py
LinkedInWebScraper/linkedin_scraper.py
LinkedInWebScraper/utils.py
OpenAIHandler/__init__.py
OpenAIHandler/openai_handler.py
Utils/__init__.py
Utils/constants.py
Utils/file_manager.py
Utils/logger.py
LinkedInWebscraper-1.0.1.dist-info/LICENSE
LinkedInWebscraper-1.0.1.dist-info/METADATA
LinkedInWebscraper-1.0.1.dist-info/WHEEL
LinkedInWebscraper-1.0.1.dist-info/top_level.txt
LinkedInWebscraper-1.0.1.dist-info/RECORD
