Metadata-Version: 2.1
Name: LinkedInWebscraper
Version: 1.0.1
Summary: A library for scraping LinkedIn job postings.
Home-page: https://github.com/ricardogr07/LinkedInWebScraper
Author: Ricardo García Ramírez
Author-email: rgr.5882@gmail.com
Classifier: Programming Language :: Python :: 3
Classifier: License :: OSI Approved :: MIT License
Classifier: Operating System :: OS Independent
Requires-Python: >=3.7
License-File: LICENSE
Requires-Dist: requests >=2.31.0
Requires-Dist: beautifulsoup4 >=4.12.3
Requires-Dist: pandas >=2.2.0
Requires-Dist: numpy >=1.26.4
Requires-Dist: openai >=1.43.0
Requires-Dist: python-dotenv >=1.0.1
